ezface/__init__.py
ezface/my_spider.py
spider_yyh-0.0.1.dist-info/METADATA
spider_yyh-0.0.1.dist-info/WHEEL
spider_yyh-0.0.1.dist-info/top_level.txt
spider_yyh-0.0.1.dist-info/RECORD
