Metadata-Version: 2.1
Name: spider-yyh
Version: 0.0.1
Summary: This project provides a simple crawler initialization steps
Home-page: https://gitee.com/one-person-line/my_snowflake_package.git
Author: YunTing
Author-email: 3336160458@qq.com
